tox_external_wheels/__init__.py
tox_external_wheels/exception.py
tox_external_wheels/plugin.py
tox_external_wheels/version.py
tox_external_wheels-0.1.8.dist-info/LICENSE
tox_external_wheels-0.1.8.dist-info/METADATA
tox_external_wheels-0.1.8.dist-info/WHEEL
tox_external_wheels-0.1.8.dist-info/entry_points.txt
tox_external_wheels-0.1.8.dist-info/top_level.txt
tox_external_wheels-0.1.8.dist-info/zip-safe
tox_external_wheels-0.1.8.dist-info/RECORD
