Metadata-Version: 2.1
Name: tox-external-wheels
Version: 0.1.8
Summary: Use externally created wheels with Tox
Home-page: http://tox-external-wheels.readthedocs.org
Author: Mark Tamas Keller
Author-email: markooo.keller@gmail.com
Maintainer: Mark Tamas Keller
Maintainer-email: markooo.keller@gmail.com
License: MIT
Project-URL: Source, https://github.com/keller00/tox-external-wheels
Project-URL: Tracker, https://github.com/keller00/tox-external-wheels/issues
Keywords: virtual,environments,isolated,testing
Platform: any
Classifier: Development Status :: 4 - Beta
Classifier: Framework :: tox
Classifier: Intended Audience :: Developers
Classifier: License :: OSI Approved :: MIT License
Classifier: Operating System :: OS Independent
Classifier: Topic :: Software Development :: Testing
Classifier: Topic :: Software Development :: Libraries
Classifier: Topic :: Utilities
Classifier: Programming Language :: Python :: 2
Classifier: Programming Language :: Python :: 2.7
Classifier: Programming Language :: Python :: 3
Classifier: Programming Language :: Python :: 3.5
Classifier: Programming Language :: Python :: 3.6
Classifier: Programming Language :: Python :: 3.7
Classifier: Programming Language :: Python :: 3.8
Requires-Python: !=3.0.*,!=3.1.*,!=3.2.*,!=3.3.*,!=3.4.*,>=2.7
License-File: LICENSE
Requires-Dist: tox (<4,>=3.12.2)
Provides-Extra: docs
Requires-Dist: sphinx (<3,>=2.0.0) ; extra == 'docs'
Requires-Dist: towncrier (>=18.5.0) ; extra == 'docs'
Requires-Dist: pygments-github-lexers (>=0.0.5) ; extra == 'docs'
Requires-Dist: sphinxcontrib-autoprogram (>=0.1.5) ; extra == 'docs'
Provides-Extra: testing
Requires-Dist: pytest (<6,>=4.0.0) ; extra == 'testing'
Requires-Dist: pytest-cov (<3,>=2.5.1) ; extra == 'testing'
Requires-Dist: pytest-mock (<2,>=1.10.0) ; extra == 'testing'
Requires-Dist: pytest-xdist (<2,>=1.22.2) ; extra == 'testing'
